setup.py
distributions_jnk1/Binomialdistribution.py
distributions_jnk1/Gaussiandistribution.py
distributions_jnk1/Generaldistribution.py
distributions_jnk1/__init__.py
distributions_jnk1.egg-info/PKG-INFO
distributions_jnk1.egg-info/SOURCES.txt
distributions_jnk1.egg-info/dependency_links.txt
distributions_jnk1.egg-info/not-zip-safe
distributions_jnk1.egg-info/top_level.txt